feboun/__init__.py
feboun/cli/__init__.py
feboun/cli/main.py
feboun/download/__init__.py
feboun/download/main.py
feboun/utils/__init__.py
feboun/utils/config.py
feboun/utils/file_path.py
feboun/web/__init__.py
feboun/web/app.py
feboun-0.0.4.dist-info/entry_points.txt
feboun-0.0.4.dist-info/LICENSE
feboun-0.0.4.dist-info/WHEEL
feboun-0.0.4.dist-info/METADATA
feboun-0.0.4.dist-info/RECORD
