Metadata-Version: 2.1
Name: feboun
Version: 0.0.4
Summary: An amazing sample package!
Author-email: Azat Y <steels-06.gasbag@icloud.com>
Classifier: License :: OSI Approved :: MIT License
Project-URL: Home, https://fe.azat.cc
